optionmodels/__init__.py
optionmodels/analyticalmethods.py
optionmodels/finitedifferencemethods.py
optionmodels/hullwhite.py
optionmodels/impliedvol.py
optionmodels/latticemethods.py
optionmodels/models.py
optionmodels/models_params.py
optionmodels/montecarlo.py
optionmodels/sabr.py
optionmodels/tools.py
optionmodels/utils.py
optionmodels-1.0.1.dist-info/LICENSE
optionmodels-1.0.1.dist-info/METADATA
optionmodels-1.0.1.dist-info/WHEEL
optionmodels-1.0.1.dist-info/top_level.txt
optionmodels-1.0.1.dist-info/RECORD
