Metadata-Version: 2.1
Name: optionmodels
Version: 1.0.1
Summary: Option pricing and volatility calibration tools
Home-page: https://github.com/GBERESEARCH/optionmodels
Author: GBERESEARCH
Author-email: gberesearch@gmail.com
License: MIT
License-File: LICENSE
Requires-Dist: numpy (>=1.16.2)
Requires-Dist: scipy (>=1.4.1)
